[
  { 
    "model": "garbage_bot.context",
    "fields": {
      "session_id": "test_session1",
      "state": 22,
      "garbage_type": null,
      "area_candidates": {
        "town_name":"旭町",
        "district_name":"1丁目"
      },
      "uuid": "test_case:ask_what",
      "created_at": "2021-03-12T15:57:00.524",
      "updated_at": "2021-03-13T17:58:00.524"
    }
  },
  { 
    "model": "garbage_bot.context",
    "fields": {
      "session_id": "test_session2",
      "state": 24,
      "garbage_type": 1,
      "area_candidates": {
        "town_name":"旭町",
        "district_name":"1丁目",
        "address_name":"nan"
      },
      "uuid": "test_case:get_day_to_collect",
      "created_at": "2021-03-12T15:57:00.524",
      "updated_at": "2021-03-13T17:58:00.524"
    }
  },
  { 
    "model": "garbage_bot.context",
    "fields": {
      "session_id": "test_session3",
      "state": 21,
      "garbage_type": null,
      "area_candidates": {
      },
      "uuid": "test_case:ask_where_state21",
      "created_at": "2021-04-12T15:57:00.524",
      "updated_at": "2021-04-13T17:58:00.524"
    }
  },
  { 
    "model": "garbage_bot.context",
    "fields": {
      "session_id": "test_session3",
      "state": 22,
      "garbage_type": null,
      "area_candidates": {
        "town_name":"旭町"
      },
      "uuid": "test_case:ask_where_state22",
      "created_at": "2021-04-12T15:57:00.524",
      "updated_at": "2021-04-13T17:58:00.524"
    }
  }
]